{
  "id": "les_advanced_006",
  "title": "ニュース記事②（イベント・お知らせ）",
  "level": "advanced",
  "order": 6,
  "description": "イベント告知の文章を学びます。",
  "content": {
    "sections": [
      {
        "type": "sentence_practice",
        "title": "イベント告知を入力しよう",
        "items": [
          {
            "text": "다음 달 15일에 서울시청 광장에서 한국 문화 축제가 열립니다.",
            "meaning": "来月15日にソウル市庁広場で韓国文化祭りが開かれます。",
            "pronunciation": "タウム ダル シボイレ ソウルシチョン クァンジャンエソ ハングク ムンファ チュクチェガ ヨルリムニダ",
            "hint": "イベント開催の表現"
          },
          {
            "text": "이번 축제에서는 전통 음악 공연, 한복 체험, 한국 음식 시식 등 다양한 프로그램이 준비되어 있습니다.",
            "meaning": "今回の祭りでは伝統音楽公演、韓服体験、韓国料理試食など様々なプログラムが準備されています。",
            "pronunciation": "イボン チュクチェエソヌン チョントン ウマク コンヨン、ハンボク チェホム、ハングク ウムシク シシク トゥン タヤンハン プログレミ チュンビドェオ イッスムニダ",
            "hint": "プログラム紹介"
          },
          {
            "text": "입장료는 무료이며 누구나 참여할 수 있습니다.",
            "meaning": "入場料は無料で誰でも参加できます。",
            "pronunciation": "イプジャンニョヌン ムリョイミョ ヌグナ チャムヨハル ス イッスムニダ",
            "hint": "参加条件"
          },
          {
            "text": "많은 관심과 참여 부탁드립니다.",
            "meaning": "多くの関心と参加をお願いします。",
            "pronunciation": "マヌン クァンシムグァ チャムヨ プタクトゥリムニダ",
            "hint": "呼びかけの表現"
          },
          {
            "text": "자세한 내용은 홈페이지를 참고해 주세요.",
            "meaning": "詳しい内容はホームページをご参照ください。",
            "pronunciation": "チャセハン ネヨンウン ホムペイジルル チャムゴヘ チュセヨ",
            "hint": "案内の表現"
          }
        ]
      }
    ]
  }
}
