{
  "id": "grm_particle_024",
  "title": "조차",
  "subtitle": "極端助詞（〜さえ）",
  "category": "particle",
  "level": "advanced",
  "tags": ["極端"],
  "content": {
    "summary": "通常期待される最小限の事柄でさえ成り立たない、または意外な対象にも及ぶことを示す強い「〜さえ／〜すら」の助詞です。多くの場合、否定や困難を伴います。",
    "formationRules": [
      {
        "condition": "名詞 + 조차",
        "form": "명사 + 조차",
        "example": "밥조차 못 먹었어요."
      },
      {
        "condition": "名詞＋도 + 조차で追加強調",
        "form": "명사 + 조차도",
        "example": "친구조차도 몰랐어요."
      },
      {
        "condition": "動詞語幹 + 기조차",
        "form": "동사 어간 + 기조차",
        "example": "읽기조차 힘들어요."
      },
      {
        "condition": "疑問詞系 + 조차で極端さを示す",
        "form": "누구/어디/언제 + 조차",
        "example": "어디인지조차 몰라요."
      },
      {
        "condition": "否定表現と共起（안/못/없다 など）",
        "form": "명사/동사 + 조차 + 부정",
        "example": "인사조차 하지 않았다."
      }
    ],
    "usageCases": [
      {
        "title": "最低限の行為すらできない",
        "description": "時間や余裕の欠如を強調する場面で用いる。",
        "examples": [
          {
            "korean": "너무 바빠서 밥조차 못 먹었어요.",
            "japanese": "忙しすぎてご飯さえ食べられませんでした。"
          }
        ]
      },
      {
        "title": "信頼していた対象すら",
        "description": "意外性・落胆を示し、期待していた対象にも及ぶことを示す。",
        "examples": [
          {
            "korean": "가장 친한 친구조차 연락이 없었어요.",
            "japanese": "一番親しい友達すら連絡がありませんでした。"
          }
        ]
      },
      {
        "title": "能力不足・困難の強調",
        "description": "初歩的なことさえ難しい状態を表す。",
        "examples": [
          {
            "korean": "한 글자 읽기조차 힘든 학생도 있어요.",
            "japanese": "一文字読むことさえ難しい学生もいます。"
          }
        ]
      },
      {
        "title": "非礼・無視を指摘",
        "description": "最低限の礼儀すら守らないことを批判する。",
        "examples": [
          {
            "korean": "인사조차 안 하고 들어갔어요.",
            "japanese": "挨拶すらせずに入っていきました。"
          }
        ]
      }
    ],
    "comparison": {
      "title": "도／까지との違い",
      "description": "도は単なる追加、까지は範囲の末端を示すのに対し、조차は「それさえも」と極端さ・意外性を伴う。通常は否定文や困難表現と結びつきます。",
      "examples": [
        {
          "grammarA": "조차",
          "sentenceA": "시간조차 없어요.",
          "meaningA": "時間すらありません。（極端な不足）",
          "grammarB": "까지",
          "sentenceB": "저녁까지 없어요.",
          "meaningB": "夕方までありません。（単なる範囲）"
        }
      ]
    },
    "tips": [
      "否定や困難とセットで使うと自然です（안/못/없다）。",
      "肯定文に使うと大げさ・不自然になるので注意しましょう。",
      "より強調したい場合は「조차도」と도を重ねます。",
      "書き言葉でやや硬い響きがあり、会話では감정語と組み合わせると効果的です。"
    ],
    "relatedGrammar": ["grm_particle_010", "grm_particle_021", "grm_particle_025"]
  },
  "exercises": [
    {
      "id": "ex_001",
      "type": "fill_blank",
      "question": "너무 바빠서 물 한 잔___ 못 마셨어요.",
      "answer": "조차",
      "hint": "「さえ」は조차を使います",
      "explanation": "名詞に直接「조차」を付けて極端な不足を表します。"
    },
    {
      "id": "ex_002",
      "type": "choice",
      "question": "「挨拶すらしなかった」を正しく表す文は？",
      "choices": [
        "인사도 안 했어요.",
        "인사조차 안 했어요.",
        "인사까지 안 했어요.",
        "인사는커녕 안 했어요."
      ],
      "answerIndex": 1,
      "explanation": "最低限の礼儀すら欠いたことを示すときは「조차」を用います。"
    },
    {
      "id": "ex_003",
      "type": "typing",
      "question": "「一文字読むことさえ難しい」を韓国語で入力してください。",
      "answer": "한 글자 읽기조차 힘들어요",
      "acceptableAnswers": ["한 글자 읽기조차 힘들어요.", "한글자 읽기조차 힘들어요", "한 글자 읽기조차 힘들어"],
      "hint": "읽기조차 + 힘들어요 の形です"
    },
    {
      "id": "ex_004",
      "type": "translation",
      "japanese": "彼は友達さえ信じなかった。",
      "answer": "그는 친구조차 믿지 않았다",
      "acceptableAnswers": ["그는 친구조차 믿지 않았다.", "그는 친구조차 안 믿었다"],
      "explanation": "信頼の対象にも及ばない意外性を示し、否定と組み合わせます。"
    },
    {
      "id": "ex_005",
      "type": "matching",
      "pairs": [
        {"left": "밥조차 못 먹었다", "right": "ご飯さえ食べられなかった"},
        {"left": "친구조차 몰랐다", "right": "友達でさえ知らなかった"},
        {"left": "읽기조차 힘들다", "right": "読むことさえ難しい"}
      ],
      "explanation": "조차が極端さ・意外性を伴う「〜さえ」を表すことを確認します。"
    }
  ]
}

