{
  "id": "grm_expression_023",
  "title": "-(으)ㄹ락 말락 하다",
  "subtitle": "曖昧表現（〜しそうでしない）",
  "category": "expression",
  "level": "advanced",
  "tags": [
    "曖昧"
  ],
  "content": {
    "summary": "行為が起こりそうで起こらない、迷い・揺れを表す「〜しそうでしない」。曖昧な態度や不安定な状況を描写します。",
    "formationRules": [
      {
        "condition": "動詞語幹 + (으)ㄹ락 말락 하다",
        "form": "동사 어간 + (으)ㄹ락 말락 하다",
        "example": "비가 올락 말락 해요."
      },
      {
        "condition": "パッチムあり → 을락 말락 / パッチムなし・ㄹ → ㄹ락 말락",
        "form": "가다 → 갈락 말락 / 먹다 → 먹을락 말락",
        "example": "잠이 올락 말락 해요."
      },
      {
        "condition": "主語・対象の揺れを描写",
        "form": "A 할락 말락 하다",
        "example": "말할락 말락 하다가 그만뒀다."
      },
      {
        "condition": "状態動詞とも使用可",
        "form": "살락 말락 하다",
        "example": "꽃이 필락 말락 해요."
      }
    ],
    "usageCases": [
      {
        "title": "天気・現象の揺れ",
        "description": "降りそうで降らないなど不安定な天候を述べる。",
        "examples": [
          {
            "korean": "비가 올락 말락 해서 우산을 가져왔어요.",
            "japanese": "雨が降りそうで降らないので傘を持ってきました。"
          }
        ]
      },
      {
        "title": "感情の揺れ",
        "description": "言い出しそうでやめるなど迷う様子を表す。",
        "examples": [
          {
            "korean": "말할락 말락 하다가 결국 안 했어요.",
            "japanese": "言いそうで言わず、結局言いませんでした。"
          }
        ]
      },
      {
        "title": "身体感覚の曖昧さ",
        "description": "眠りに落ちそうなど境界状態を述べる。",
        "examples": [
          {
            "korean": "잠이 올락 말락 해서 집중이 안 돼요.",
            "japanese": "眠りそうで眠れず集中できません。"
          }
        ]
      },
      {
        "title": "未確定な動き",
        "description": "行きそうで行かない、参加しそうでしないなど曖昧な動き。",
        "examples": [
          {
            "korean": "갈락 말락 하다가 집에 있었어요.",
            "japanese": "行こうかと思いながら行かず家にいました。"
          }
        ]
      }
    ],
    "comparison": {
      "title": "-듯 말듯 vs -(으)ㄹ락 말락",
      "description": "둘 다曖昧さを示すが, -듯 말듯 はより書き言葉で描写的。-(으)ㄹ락 말락 は会話的で揺れを強調する。",
      "examples": [
        {
          "grammarA": "-(으)ㄹ락 말락",
          "sentenceA": "비가 올락 말락 한다.",
          "meaningA": "雨が降りそうで降らない。",
          "grammarB": "-듯 말듯",
          "sentenceB": "비가 올 듯 말 듯 하다.",
          "meaningB": "雨が降りそうで降らなさそうだ。（描写的）"
        }
      ]
    },
    "tips": [
      "揺れを出したいので同じ動詞を繰り返す形を保ちます.",
      "会話では発音簡略型「을라 말라」も耳にします.",
      "後件に判断や行動を続けると自然です（…해서 …했다).",
      "肯定否定どちらとも言えない曖昧さを意識して使いましょう."
    ],
    "relatedGrammar": [
      "grm_expression_021",
      "grm_expression_025",
      "grm_connective_019"
    ]
  },
  "exercises": [
    {
      "id": "ex_001",
      "type": "fill_blank",
      "question": "비가 올락 말락 ___ 우산을 가져왔어요.",
      "answer": "해서",
      "hint": "理由をつなげます",
      "explanation": "올락 말락 하다 で曖昧な状態を表し、その結果を 이어줍니다."
    },
    {
      "id": "ex_002",
      "type": "choice",
      "question": "「言いそうで言わなかった」を表す正しい文は？",
      "choices": [
        "말할락 말락 하다가 안 했다.",
        "말하고 말았다.",
        "말하려고 했다.",
        "말할까 말까 했다."
      ],
      "answerIndex": 0,
      "explanation": "曖昧に揺れたことを強調するには -(으)ㄹ락 말락 하다 를 사용합니다."
    },
    {
      "id": "ex_003",
      "type": "typing",
      "question": "「眠りそうで眠れず集中できません」を韓国語で入力してください.",
      "answer": "잠이 올락 말락 해서 집중이 안 돼요",
      "acceptableAnswers": [
        "잠이 올락 말락 해서 집중이 안 돼요.",
        "잠이 올락 말락 해서 집중이 안 됩니다"
      ],
      "hint": "올락 말락 하다 の形を保ちます"
    },
    {
      "id": "ex_004",
      "type": "translation",
      "japanese": "行こうかと思いながら行かず家にいた。",
      "answer": "갈락 말락 하다가 집에 있었다",
      "acceptableAnswers": [
        "갈락 말락 하다가 집에 있었다.",
        "갈락 말락 하다가 집에 있었어요"
      ],
      "explanation": "行きそうで行かない揺れを -(으)ㄹ락 말락 하다 で表現します."
    }
  ]
}
