{
  "id": "grm_interrogative_005",
  "title": "왜",
  "subtitle": "疑問副詞（なぜ）",
  "category": "interrogative",
  "level": "beginner",
  "tags": ["理由"],
  "content": {
    "summary": "理由や原因を尋ねる疑問詞で、日本語の「なぜ」「どうして」に当たります。語尾との組み合わせで丁寧さやニュアンスが変わります。",
    "formationRules": [
      {
        "condition": "基本形",
        "form": "왜 + V?",
        "example": "왜 늦었어요? (なぜ遅れましたか？)"
      },
      {
        "condition": "理由を柔らかく尋ねる",
        "form": "왜요?/왜 그렇게요?",
        "example": "왜요? 무슨 일 있어요? (どうしたんですか？何かありましたか？)"
      },
      {
        "condition": "肯定形で答えるとき",
        "form": "왜냐하면 ~ (からです)",
        "example": "왜냐하면 일이 많아요. (なぜなら仕事が多いからです。)"
      }
    ],
    "usageCases": [
      {
        "title": "理由を直接尋ねる",
        "description": "相手の行動・状況の原因を知りたいときに使います。",
        "examples": [
          {
            "korean": "왜 울어요?",
            "japanese": "なぜ泣いているのですか。"
          }
        ]
      },
      {
        "title": "不満や驚きを含む問いかけ",
        "description": "驚きや軽い非難を込めて理由を尋ねる場合に用います。",
        "examples": [
          {
            "korean": "왜 그렇게 비싸요?",
            "japanese": "どうしてそんなに高いんですか。"
          }
        ]
      },
      {
        "title": "背景説明を促す",
        "description": "相手に事情や経緯を説明してもらいたいときに使います。",
        "examples": [
          {
            "korean": "왜 안 왔는지 말해 주세요.",
            "japanese": "なぜ来なかったのか教えてください。"
          }
        ]
      }
    ],
    "comparison": {
      "title": "왜 と 어떻게 된 거야?",
      "description": "왜 は理由を直接尋ねる疑問詞、어떻게 된 거야? は状況の経緯・経過を尋ねる表現です。理由を丁寧に聞きたいときは '무슨 이유로' も使います。",
      "examples": [
        {
          "grammarA": "왜",
          "sentenceA": "왜 지각했어요?",
          "meaningA": "なぜ遅刻したのですか。",
          "grammarB": "어떻게 된 거야?",
          "sentenceB": "어떻게 된 거야? 무슨 일 있었어?",
          "meaningB": "どうなったの？何があったの？"
        }
      ]
    },
    "tips": [
      "強い口調で言うと責めるニュアンスになるので、왜요? や 이유가 궁금해요 のように柔らかくできます。",
      "返答では 그래서/왜냐하면 を添えると自然です。",
      "フォーマルに理由を尋ねるときは '무슨 이유로 오셨습니까?' のように言い換えます。"
    ],
    "relatedGrammar": ["grm_connective_003", "grm_connective_011", "grm_interrogative_006"]
  },
  "exercises": [
    {
      "id": "ex_001",
      "type": "fill_blank",
      "question": "___ 이렇게 늦었어요?",
      "answer": "왜",
      "hint": "理由を尋ねる疑問詞を入れます。",
      "explanation": "「なぜ〜？」は 왜 + 動詞で尋ねます。"
    },
    {
      "id": "ex_002",
      "type": "choice",
      "question": "『왜요? 무슨 일 있어요?』のニュアンスは？",
      "choices": [
        "理由をやわらかく尋ねている",
        "相手を強く責めている",
        "場所を尋ねている",
        "方法を尋ねている"
      ],
      "answerIndex": 0,
      "explanation": "왜요? と丁寧語尾を使うと柔らかい尋ね方になります。"
    },
    {
      "id": "ex_003",
      "type": "typing",
      "question": "「なぜ来なかったのか教えてください」を韓国語で入力してください",
      "answer": "왜 안 왔는지 말해 주세요.",
      "acceptableAnswers": ["왜 안 왔는지 말해 주세요.", "왜 안 왔는지 말해 주세요"],
      "hint": "理由+間接疑問には -는지 を使います。"
    }
  ],
  "metadata": {
    "createdAt": "2025-12-07T00:00:00Z",
    "updatedAt": "2025-12-07T00:00:00Z",
    "version": "1.0.0"
  }
}
